number_precision/__init__.py
number_precision/number_precision.py
number_precision-2021.1.30.dist-info/LICENSE
number_precision-2021.1.30.dist-info/METADATA
number_precision-2021.1.30.dist-info/WHEEL
number_precision-2021.1.30.dist-info/top_level.txt
number_precision-2021.1.30.dist-info/RECORD
