Metadata-Version: 2.1
Name: number-precision
Version: 2021.1.30
Summary: Python 精度计算
Home-page: https://github.com/Czw96/NumberPrecision
Author: Czzwww
Author-email: 459749926@qq.com
License: UNKNOWN
Platform: UNKNOWN
Classifier: Programming Language :: Python :: 3
Classifier: License :: OSI Approved :: MIT License
Classifier: Operating System :: OS Independent
